AUTHORS.rst
CONTRIBUTING.rst
HISTORY.rst
LICENSE
MANIFEST.in
README.rst
setup.cfg
setup.py
docs/Makefile
docs/authors.rst
docs/conf.py
docs/contributing.rst
docs/history.rst
docs/index.rst
docs/installation.rst
docs/make.bat
docs/readme.rst
docs/usage.rst
email_ddns.egg-info/PKG-INFO
email_ddns.egg-info/SOURCES.txt
email_ddns.egg-info/dependency_links.txt
email_ddns.egg-info/entry_points.txt
email_ddns.egg-info/not-zip-safe
email_ddns.egg-info/requires.txt
email_ddns.egg-info/top_level.txt
emailddns/__init__.py
emailddns/__main__.py
emailddns/emailddns.py
emailddns/exceptions.py
tests/__init__.py
tests/test_emailddns.py