Metadata-Version: 1.1
Name: email-ddns
Version: 0.0.2
Summary: A DDNS server/client that only rely on free services (email, outer ip getter)
Home-page: https://github.com/starofrainnight/email-ddns
Author: Hong-She Liang
Author-email: starofrainnight@gmail.com
License: GNU Affero General Public License v3
Keywords: emailddns,email-ddns
Platform: UNKNOWN
Classifier: Development Status :: 2 - Pre-Alpha
Classifier: Intended Audience :: Developers
Classifier: License :: OSI Approved :: GNU Affero General Public License v3
Classifier: Natural Language :: English
Classifier: Programming Language :: Python :: 3
Classifier: Programming Language :: Python :: 3.4
Classifier: Programming Language :: Python :: 3.5
Classifier: Programming Language :: Python :: 3.6
